ecs_dns/__init__.py
ecs_dns/_cli.py
ecs_dns/_ecs_dns.py
ecs_dns/models.py
ecs_dns-0.1.13.dist-info/LICENSE
ecs_dns-0.1.13.dist-info/METADATA
ecs_dns-0.1.13.dist-info/WHEEL
ecs_dns-0.1.13.dist-info/entry_points.txt
ecs_dns-0.1.13.dist-info/top_level.txt
ecs_dns-0.1.13.dist-info/RECORD
