Metadata-Version: 2.1
Name: ecs-dns
Version: 0.1.13
Summary: Creates a Route 53 CNAME for ECS tasks which are assigned a public IP.
Home-page: https://github.com/inhumantsar/ecs-dns
Author: Shaun Martin
Author-email: inhumantsar@protonmail.com
License: BSD license
Download-URL: https://github.com/inhumantsar/ecs-dns/archive/refs/tags/v0.1.13.zip
Project-URL: Repository, https://github.com/inhumantsar/ecs-dns
Project-URL: Bug Reports, https://github.com/inhumantsar/ecs-dns/issues
Platform: any
Classifier: Development Status :: 3 - Alpha
Classifier: Intended Audience :: Developers
Classifier: License :: OSI Approved :: MIT License
Classifier: Operating System :: OS Independent
Classifier: Programming Language :: Python :: 3.6
Classifier: Programming Language :: Python :: 3.7
Classifier: Programming Language :: Python :: 3.8
Classifier: Programming Language :: Python :: 3.9
Requires-Python: >=3.6.0
License-File: LICENSE
Requires-Dist: boto3 (>=1.18.28)
Requires-Dist: requests (>=2.26.0)
Requires-Dist: click (>=8.0.1)
